fastapi_pagination/__init__.py
tests/__init__.py
tests/test_pagination.py
fastapi_pagination_utilities-0.9.1.dist-info/COPYING
fastapi_pagination_utilities-0.9.1.dist-info/METADATA
fastapi_pagination_utilities-0.9.1.dist-info/WHEEL
fastapi_pagination_utilities-0.9.1.dist-info/top_level.txt
fastapi_pagination_utilities-0.9.1.dist-info/RECORD
