Metadata-Version: 2.1
Name: fastapi-pagination-utilities
Version: 0.9.1
Summary: A module containing helpers for paginating responses with FastAPI
Home-page: https://gitlab.developers.cam.ac.uk/uis/devops/lib/fastapi-pagination
Author: University of Cambridge Information Services
Author-email: devops+fastapi-pagination-utilities@uis.cam.ac.uk
License: MIT
Classifier: Programming Language :: Python :: 3
Classifier: License :: OSI Approved :: MIT License
Classifier: Development Status :: 4 - Beta
Classifier: Intended Audience :: Developers
Classifier: License :: OSI Approved :: MIT License
Classifier: Operating System :: OS Independent
License-File: COPYING
Requires-Dist: fastapi (>=0.68.0)
Requires-Dist: requests (~=2.26)
Requires-Dist: pyhumps (~=3.0)
